zodchy_fastapi/__init__.py
zodchy_fastapi/factory.py
zodchy_fastapi/middleware.py
zodchy_fastapi/py.typed
zodchy_fastapi/request.py
zodchy_fastapi/response.py
zodchy_fastapi/serializing.py
zodchy_fastapi/definition/__init__.py
zodchy_fastapi/definition/contracts.py
zodchy_fastapi/definition/schema/__init__.py
zodchy_fastapi/definition/schema/request.py
zodchy_fastapi/definition/schema/response.py
zodchy_fastapi/patterns/__init__.py
zodchy_fastapi/patterns/handlers.py
zodchy_fastapi/patterns/interceptors.py
zodchy_fastapi/routing/__init__.py
zodchy_fastapi/routing/endpoint.py
zodchy_fastapi/routing/registry.py
zodchy_fastapi/routing/router.py
zodchy_fastapi-2.4.1.dist-info/METADATA
zodchy_fastapi-2.4.1.dist-info/WHEEL
zodchy_fastapi-2.4.1.dist-info/RECORD
