Metadata-Version: 2.4
Name: zodchy-fastapi
Version: 2.4.1
Summary: Zodchy FastAPI - FastAPI integration for zodchy architecture
Project-URL: Homepage, https://github.com/smairon/zodchy-fastapi
Project-URL: Documentation, https://smairon.github.io/zodchy-fastapi
Project-URL: Repository, https://github.com/smairon/zodchy-fastapi
Project-URL: Changelog, https://github.com/smairon/zodchy-fastapi/releases
Project-URL: Issues, https://github.com/smairon/zodchy-fastapi/issues
Author-email: Smairon <man@smairon.ru>
License: MIT
Keywords: architecture,fastapi,python,zodchy
Classifier: Development Status :: 3 - Alpha
Classifier: Intended Audience :: Developers
Classifier: License :: OSI Approved :: MIT License
Classifier: Operating System :: OS Independent
Classifier: Programming Language :: Python :: 3
Classifier: Programming Language :: Python :: 3.11
Classifier: Programming Language :: Python :: 3.12
Classifier: Programming Language :: Python :: 3.13
Classifier: Programming Language :: Python :: 3.14
Requires-Python: >=3.11
Requires-Dist: fastapi>=0.121.1
Requires-Dist: pyjwt>=2.10.1
Requires-Dist: zodchy>=1.0.3
Provides-Extra: dev
Requires-Dist: bandit>=1.7.0; extra == 'dev'
Requires-Dist: black>=23.0.0; extra == 'dev'
Requires-Dist: mypy>=1.0.0; extra == 'dev'
Requires-Dist: pre-commit>=3.0.0; extra == 'dev'
Requires-Dist: pytest-asyncio>=0.21.0; extra == 'dev'
Requires-Dist: pytest-cov>=4.0.0; extra == 'dev'
Requires-Dist: pytest-xdist>=3.0.0; extra == 'dev'
Requires-Dist: pytest>=7.0.0; extra == 'dev'
Requires-Dist: ruff>=0.1.0; extra == 'dev'
Requires-Dist: safety>=2.0.0; extra == 'dev'
Requires-Dist: uvicorn>=0.34.0; extra == 'dev'
Provides-Extra: docs
Requires-Dist: mkdocs-material>=9.0.0; extra == 'docs'
Requires-Dist: mkdocs>=1.5.0; extra == 'docs'
Requires-Dist: mkdocstrings[python]>=0.22.0; extra == 'docs'
